opod/__init__.py
opod/__version__.py
opod/api.py
opod/cli.py
opod/core.py
opod-0.0.1.dist-info/LICENSE
opod-0.0.1.dist-info/METADATA
opod-0.0.1.dist-info/WHEEL
opod-0.0.1.dist-info/entry_points.txt
opod-0.0.1.dist-info/top_level.txt
opod-0.0.1.dist-info/RECORD
