Metadata-Version: 2.1
Name: opod
Version: 0.0.1
Summary: Use opod orchestrate Podman
Home-page: https://pypi.org/project/opod/
Author: Brian Farrell
Author-email: brian.farrell@me.com
License: AGPLv3
Keywords: Podman docker-compose orchestration
Platform: UNKNOWN
Classifier: Development Status :: 1 - Planning
Classifier: Intended Audience :: End Users/Desktop
Classifier: License :: OSI Approved :: GNU Affero General Public License v3
Classifier: Environment :: Console
Classifier: Programming Language :: Python
Classifier: Programming Language :: Python :: 3
Classifier: Programming Language :: Python :: Implementation :: CPython
Requires-Python: >=3.6.0
